built/__init__.py
built/builder.py
built/checkpoint_manager.py
built/early_stopper.py
built/ensembler.py
built/evaluation_scheduler.py
built/forward_hook.py
built/inference.py
built/logger.py
built/loss.py
built/metric.py
built/optimizer_param.py
built/registry.py
built/singleton_decorator.py
built/splitter.py
built/trainer_base.py
built/transform.py
built/models/__init__.py
built/models/mnist.py
built/models/backbones/__init__.py
built/models/backbones/efficientnet.py
built/models/backbones/resnext.py
built/utils/__init__.py
built/utils/kaggle_helper.py
built/utils/smooth_label_loss.py
built/utils/util_functions.py
tests/__init__.py
tests/test_checkpoint_manager.py
tests/test_early_stopper.py
tests/test_evaluation_scheduler.py
tests/test_registry.py
tests/test_sweep.py
tests/test_trainer.py
BuilT-0.0.4.dist-info/LICENSE
BuilT-0.0.4.dist-info/METADATA
BuilT-0.0.4.dist-info/WHEEL
BuilT-0.0.4.dist-info/top_level.txt
BuilT-0.0.4.dist-info/RECORD
