Metadata-Version: 2.1
Name: BuilT
Version: 0.0.4
Summary: Easily build your trainer for DNNs.
Home-page: https://github.com/UoA-CARES/BuilT
Author: JongYoon Lim
Author-email: jy.lim@auckland.ac.nz
License: UNKNOWN
Project-URL: Bug Tracker, https://github.com/UoA-CARES/BuilT/issues
Platform: UNKNOWN
Classifier: Programming Language :: Python :: 3
Classifier: License :: OSI Approved :: MIT License
Classifier: Operating System :: OS Independent
Requires-Python: >=3.7
License-File: LICENSE
Requires-Dist: easydict
Requires-Dist: PyYAML
Requires-Dist: torch
Requires-Dist: torchvision
Requires-Dist: pandas
Requires-Dist: wandb
Requires-Dist: sklearn
Requires-Dist: tqdm
